panoramisk/__init__.py
panoramisk/actions.py
panoramisk/ami_protocol.py
panoramisk/call_manager.py
panoramisk/command.py
panoramisk/fast_agi.py
panoramisk/manager.py
panoramisk/message.py
panoramisk/testing.py
panoramisk/utils.py
panoramisk-1.4.dist-info/LICENSE
panoramisk-1.4.dist-info/METADATA
panoramisk-1.4.dist-info/WHEEL
panoramisk-1.4.dist-info/entry_points.txt
panoramisk-1.4.dist-info/top_level.txt
panoramisk-1.4.dist-info/RECORD
