Metadata-Version: 2.1
Name: panoramisk
Version: 1.4
Summary: asyncio based library to play with asterisk
Home-page: https://github.com/gawel/panoramisk/
Author: Gael Pasgrimaud
Author-email: gael@gawel.org
License: MIT license
Keywords: asyncio,asterisk,voip
Platform: UNKNOWN
Classifier: Development Status :: 5 - Production/Stable
Classifier: Intended Audience :: Developers
Classifier: License :: OSI Approved :: MIT License
Classifier: Operating System :: OS Independent
Classifier: Programming Language :: Python
Classifier: Programming Language :: Python :: 3.4
Classifier: Programming Language :: Python :: 3.5
Classifier: Topic :: Communications :: Telephony
Classifier: Topic :: Software Development :: Libraries :: Python Modules
Provides-Extra: test
